LICENSE
MANIFEST.in
README.md
setup.py
Faab/Faab.py
Faab/FaabFunction.py
Faab/FaabJWT.py
Faab/__init__.py
Faab/__version__.py
Faab/extensions.py
Faab/factory.py
Faab/utils.py
Faab.egg-info/PKG-INFO
Faab.egg-info/SOURCES.txt
Faab.egg-info/dependency_links.txt
Faab.egg-info/requires.txt
Faab.egg-info/top_level.txt
Faab/swag_config/__init__.py
Faab/swag_config/delete.yml
Faab/swag_config/export.yml
Faab/swag_config/get.yml
Faab/swag_config/get_one.yml
Faab/swag_config/post.yml
Faab/swag_config/put.yml