Metadata-Version: 2.1
Name: Faab
Version: 0.1.9
Summary: This tool has the capability to automatically generate API endpoints based on the provided data model or database schema, encompassing operations such as creation, retrieval, updating, and deletion (CRUD). By doing so, it alleviates the burden on developers to manually write and configure these API endpoints, thus enhancing development efficiency. Furthermore, it can generate Swagger documentation, facilitating API debugging.
Author: Mao
Author-email: deewpoter@163.com
License: GLP
Classifier: Programming Language :: Python
Classifier: Programming Language :: Python :: 3
Classifier: Programming Language :: Python :: 3.6
Classifier: Programming Language :: Python :: Implementation :: CPython
Classifier: Programming Language :: Python :: Implementation :: PyPy
Requires-Python: >=3.6.0
License-File: LICENSE
Requires-Dist: flask
Requires-Dist: flask-sqlalchemy
Requires-Dist: pymysql
Requires-Dist: PyJWT
Requires-Dist: Flask-Cors
Requires-Dist: Pillow
Requires-Dist: ffmpeg-python
Requires-Dist: werkzeug
